ovp_docker_manager/__init__.py
ovp_docker_manager/defaults.py
ovp_docker_manager/docker_compose_instance.py
ovp_docker_manager/oem_logging.py
ovp_docker_manager/ovp_docker_manager.py
ovp_docker_manager/ssh_file_utils.py
ovp_docker_manager-1.0.0.dist-info/LICENSE
ovp_docker_manager-1.0.0.dist-info/METADATA
ovp_docker_manager-1.0.0.dist-info/WHEEL
ovp_docker_manager-1.0.0.dist-info/entry_points.txt
ovp_docker_manager-1.0.0.dist-info/top_level.txt
ovp_docker_manager-1.0.0.dist-info/RECORD
