Metadata-Version: 2.1
Name: ovp_docker_manager
Version: 1.0.0
Summary: O3R docker deployment utilities
Author: ifm gmbh
License-File: LICENSE
Requires-Dist: pyyaml
Requires-Dist: scp
Requires-Dist: ifm3dpy
Requires-Dist: pydantic
